pukala/__init__.py
pukala/fs_binding.py
pukala/pukala.py
pukala-1.0.3.dist-info/DESCRIPTION.rst
pukala-1.0.3.dist-info/METADATA
pukala-1.0.3.dist-info/RECORD
pukala-1.0.3.dist-info/WHEEL
pukala-1.0.3.dist-info/metadata.json
pukala-1.0.3.dist-info/top_level.txt
