Metadata-Version: 2.0
Name: pukala
Version: 1.0.3
Summary: dict/list tree generator for cluster deployment
Home-page: https://gitlab.com/paulsj-80/pukala.git
Author: Pauls Jakovels
Author-email: pauls.jakovels@gmail.com
License: MIT
Project-URL: Source, https://gitlab.com/paulsj-80/pukala
Project-URL: Documentation, https://gitlab.com/paulsj-80/pukala/blob/master/README.md
Keywords: yaml tree cluster autodeployment
Platform: UNKNOWN
Classifier: Development Status :: 4 - Beta
Classifier: Intended Audience :: Developers
Classifier: Topic :: Software Development :: Build Tools
Classifier: License :: OSI Approved :: MIT License
Classifier: Programming Language :: Python :: 2
Classifier: Programming Language :: Python :: 2.6
Classifier: Programming Language :: Python :: 2.7
Requires-Python: >2.6, <3
Requires-Dist: pyyaml
Requires-Dist: simplejson
